README.rst
setup.py
ardurpc/__about__.py
ardurpc/__init__.py
ardurpc/exception.py
ardurpc.egg-info/PKG-INFO
ardurpc.egg-info/SOURCES.txt
ardurpc.egg-info/dependency_links.txt
ardurpc.egg-info/not-zip-safe
ardurpc.egg-info/top_level.txt
ardurpc/connector/__init__.py
ardurpc/connector/bluetooth_con.py
ardurpc/connector/ethernet_con.py
ardurpc/connector/serial_con.py
ardurpc/handler/__init__.py
ardurpc/handler/board.py
ardurpc/handler/lcd/__init__.py
ardurpc/handler/matrix/__init__.py
ardurpc/handler/sensor/__init__.py
ardurpc/handler/sensor/temperature_humidity.py
ardurpc/handler/strip/__init__.py