Metadata-Version: 1.1
Name: ardurpc
Version: 0.3
Summary: An extensible library to control microcontroller boards like Arduino using Python and the ArduRPC protocol
Home-page: https://github.com/DinoTools/ArduRPC-python
Author: PhiBo (DinoTools)
Author-email: UNKNOWN
License: LGPLv3+
Platform: UNKNOWN
Classifier: Development Status :: 3 - Alpha
Classifier: Environment :: Console
Classifier: Intended Audience :: Developers
Classifier: License :: OSI Approved :: GNU Lesser General Public License v3 or later (LGPLv3+)
Classifier: Operating System :: POSIX
Classifier: Operating System :: POSIX :: Linux
Classifier: Programming Language :: Python
Classifier: Programming Language :: Python :: 3
Classifier: Programming Language :: Python :: 3.0
Classifier: Programming Language :: Python :: 3.1
Classifier: Programming Language :: Python :: 3.2
Classifier: Programming Language :: Python :: 3.3
